agipack/builder.py
agipack/cli.py
agipack/config.py
agipack/constants.py
agipack/version.py
agipack/templates/Dockerfile.j2
agipack/templates/agibuild.sample.yaml
agi_pack-0.3.0.dist-info/LICENSE
agi_pack-0.3.0.dist-info/METADATA
agi_pack-0.3.0.dist-info/WHEEL
agi_pack-0.3.0.dist-info/entry_points.txt
agi_pack-0.3.0.dist-info/top_level.txt
agi_pack-0.3.0.dist-info/RECORD
