Metadata-Version: 2.1
Name: agi-pack
Version: 0.3.0
Summary: Dockerfile generator for AGI -- nothing more, nothing less.
License: MIT License
Project-URL: Documentation, https://spillai.github.io/agi-pack/
Project-URL: Source Code, https://github.com/spillai/agi-pack
Project-URL: Homepage, https://spillai.github.io/agi-pack/
Classifier: Development Status :: 4 - Beta
Classifier: Programming Language :: Python
Classifier: Environment :: Console
Classifier: Intended Audience :: Developers
Classifier: Intended Audience :: Information Technology
Classifier: Intended Audience :: Science/Research
Classifier: Topic :: Software Development :: Libraries
Classifier: Topic :: Scientific/Engineering :: Artificial Intelligence
Classifier: License :: OSI Approved :: MIT License
Classifier: Programming Language :: Python :: 3 :: Only
Classifier: Programming Language :: Python :: 3.7
Classifier: Programming Language :: Python :: 3.8
Classifier: Programming Language :: Python :: 3.9
Classifier: Programming Language :: Python :: 3.10
Classifier: Programming Language :: Python :: 3.11
Requires-Python: >=3.7
License-File: LICENSE
Requires-Dist: jinja2
Requires-Dist: pydantic >=2.5
Requires-Dist: pyyaml
Requires-Dist: typer[all]
Provides-Extra: dev
Requires-Dist: pre-commit ; extra == 'dev'
Requires-Dist: pytest ; extra == 'dev'
Requires-Dist: build ; extra == 'dev'
